pyHand/__init__.py
pyHand-1.0.1.dist-info/LICENSE
pyHand-1.0.1.dist-info/METADATA
pyHand-1.0.1.dist-info/WHEEL
pyHand-1.0.1.dist-info/top_level.txt
pyHand-1.0.1.dist-info/RECORD
