Metadata-Version: 2.1
Name: pyHand
Version: 1.0.1
Summary: pyHand
Home-page: UNKNOWN
Author: SujithSouryaYedida
Author-email: sujithsourya.yedida@gmail.com
License: UNKNOWN
Keywords: handwritten,python,hand,text,SujithSouryaYedida,py,text to handwritten,write,written,pip
Platform: UNKNOWN
Classifier: Development Status :: 1 - Planning
Classifier: Intended Audience :: Developers
Classifier: Programming Language :: Python :: 3
Classifier: Operating System :: Unix
Classifier: Operating System :: MacOS :: MacOS X
Classifier: Operating System :: Microsoft :: Windows
License-File: LICENSE
Requires-Dist: colorama
Requires-Dist: pyfiglet
Requires-Dist: pywhatkit
